moelib/__init__.py
moelib/__main__.py
moelib-0.1.3.dist-info/LICENSE
moelib-0.1.3.dist-info/METADATA
moelib-0.1.3.dist-info/WHEEL
moelib-0.1.3.dist-info/entry_points.txt
moelib-0.1.3.dist-info/RECORD
