Metadata-Version: 2.1
Name: moelib
Version: 0.1.3
Summary: 
Home-page: https://github.com/ShigureLab/moelib
License: MIT
Author: Nyakku Shigure
Author-email: sigure.qaq@gmail.com
Requires-Python: >=3.9,<4.0
Classifier: License :: OSI Approved :: MIT License
Classifier: Operating System :: OS Independent
Classifier: Programming Language :: Python
Classifier: Programming Language :: Python :: 3
Classifier: Programming Language :: Python :: 3.9
Classifier: Programming Language :: Python :: 3.10
Classifier: Programming Language :: Python :: 3.11
Classifier: Programming Language :: Python :: Implementation :: CPython
Project-URL: Repository, https://github.com/ShigureLab/moelib
